README.rst
setup.py
txeasymail/__init__.py
txeasymail/html.py
txeasymail/interface.py
txeasymail/mailer.py
txeasymail/markdown.py
txeasymail/mime.py
txeasymail.egg-info/PKG-INFO
txeasymail.egg-info/SOURCES.txt
txeasymail.egg-info/dependency_links.txt
txeasymail.egg-info/requires.txt
txeasymail.egg-info/top_level.txt
txeasymail/test/__init__.py