Metadata-Version: 1.1
Name: txeasymail
Version: 20121112
Summary: Twisted client for easy email sending
Home-page: https://github.com/lvh/txeasymail
Author: Laurens Van Houtven
Author-email: _@lvh.cc
License: ISC
Platform: UNKNOWN
Classifier: Development Status :: 3 - Alpha
Classifier: Framework :: Twisted
Classifier: License :: OSI Approved :: ISC License (ISCL)
